LICENSE.txt
README.rst
setup.cfg
setup.py
kittiprofile/__init__.py
kittiprofile/myprofile.py
kittiprofile.egg-info/PKG-INFO
kittiprofile.egg-info/SOURCES.txt
kittiprofile.egg-info/dependency_links.txt
kittiprofile.egg-info/top_level.txt